Workbook

Sheet Instructions
A1: Global Logistics Corp — GenAIOps cost model
A2: Purpose
A3: Use this workbook to estimate monthly model-token cost, test low/base/high agent sensitivity cases, allocate spend, set quota guardrails, and model optimization scenarios. Green cells are editable assumptions. Derived values use formulas.
A5: Required use rules
A6: 1 | B6: Replace the illustrative input and output rates with the contracted model/SKU rates before production use.
A7: 2 | B7: Treat 5×, 12×, and 30× only as low/base/high sensitivity inputs. They are not an industry benchmark.
A8: 3 | B8: Replace the agent multiplier with measured model calls, tool-context tokens, retries, and outputs from traces.
A9: 4 | B9: Reconcile allocation totals to Azure Cost Management or the enterprise invoice. Gateway counters are not the financial ledger.
A10: 5 | B10: Token-rate and quota enforcement can be temporarily imprecise in distributed systems. Use alert buffers and reconciliation.
A11: 6 | B11: Do not accept a cost reduction that violates quality, safety, privacy, or availability SLOs.
A12: Workbook map
A13: Inputs | B13: Editable prices, multipliers, budget thresholds, and application assumptions.
A14: Token Cost Model | B14: Formula-driven monthly token and cost calculations for each application.
A15: Agent Sensitivity | B15: Low/base/high agent cases with formula-driven costs.
A16: Chargeback & Quotas | B16: Cost-center allocation, budget utilization, and recommended enforcement controls.
A17: Optimization Scenarios | B17: Savings cases with quality and safety guardrails.
A18: Sources | B18: Product and legal validation notes. Links must be checked at implementation time.

Sheet Inputs
A1: Editable assumptions
A2: Assumption | B2: Value | C2: Notes
A3: Input token rate per 1M | B3: 2.5 | C3: Illustrative only; replace with contracted SKU
A4: Output token rate per 1M | B4: 10 | C4: Illustrative only; replace with contracted SKU
A5: Agent low multiplier | B5: 5 | C5: Sensitivity case only
A6: Agent base multiplier | B6: 12 | C6: Course planning case; replace with traces
A7: Agent high multiplier | B7: 30 | C7: Stress case only
A8: Soft budget alert | B8: 0.7 | C8: Notify owner and FinOps
A9: Escalation alert | B9: 0.85 | C9: Require optimization or exception plan
A10: Hard quota threshold | B10: 1 | C10: Use only where business impact is acceptable
A11: Optimization base case | B11: 0.25 | C11: Planning case, not guaranteed
A12: Monthly GenAI budget | B12: 50000 | C12: Course assumption
A13: Application assumptions
A14: Application ID | B14: Application name | C14: Monthly tasks | D14: Input tokens/base task | E14: Output tokens/base task | F14: Calls/task | G14: Multiplier | H14: Cost center | I14: Monthly budget | J14: Notes
A15: GLC-CX-Chat | B15: Customer support chatbot | C15: 2000000 | D15: 900 | E15: 250 | F15: 1 | G15: 1 | H15: Customer Experience | I15: 12000 | J15: No executable tools
A16: GLC-NetAssist | B16: Network-optimization assistant | C16: 300000 | D16: 1800 | E16: 600 | F16: 1 | G16: 1 | H16: Network Operations | I16: 8000 | J16: Recommendations only
A17: GLC-DocSum | B17: Shipment-document summarizer | C17: 500000 | D17: 3000 | E17: 500 | F17: 1 | G17: 1 | H17: Document Operations | I17: 15000 | J17: Document-attack controls
A18: GLC-ExceptionAgent | B18: Exception-handling agent | C18: 60000 | D18: 900 | E18: 250 | F18: 1 | G18: =B6 -> 12 | H18: Exception Operations | I18: 15000 | J18: Base multiplier links to Agent base multiplier

Sheet Token Cost Model
A1: Monthly token cost model — base case
A2: Formula logic: tasks × base tokens × calls per task × multiplier. Agent values are planning assumptions until replaced with trace-based measurements.
A3: Application ID | B3: Application name | C3: Monthly tasks | D3: Input tokens/base task | E3: Output tokens/base task | F3: Calls/task | G3: Multiplier | H3: Monthly input tokens | I3: Monthly output tokens | J3: Input rate/1M | K3: Output rate/1M | L3: Monthly cost | M3: Cost/task | N3: Cost center
A4: =Inputs!A15 -> GLC-CX-Chat | B4: =Inputs!B15 -> Customer support chatbot | C4: =Inputs!C15 -> 2000000 | D4: =Inputs!D15 -> 900 | E4: =Inputs!E15 -> 250 | F4: =Inputs!F15 -> 1 | G4: =Inputs!G15 -> 1 | H4: =C4*D4*F4*G4 -> 1800000000 | I4: =C4*E4*F4*G4 -> 500000000 | J4: =Inputs!$B$3 -> 2.5 | K4: =Inputs!$B$4 -> 10 | L4: =(H4/1000000)*J4+(I4/1000000)*K4 -> 9500 | M4: =IFERROR(L4/C4,0) -> 0.00475 | N4: =Inputs!H15 -> Customer Experience
A5: =Inputs!A16 -> GLC-NetAssist | B5: =Inputs!B16 -> Network-optimization assistant | C5: =Inputs!C16 -> 300000 | D5: =Inputs!D16 -> 1800 | E5: =Inputs!E16 -> 600 | F5: =Inputs!F16 -> 1 | G5: =Inputs!G16 -> 1 | H5: =C5*D5*F5*G5 -> 540000000 | I5: =C5*E5*F5*G5 -> 180000000 | J5: =Inputs!$B$3 -> 2.5 | K5: =Inputs!$B$4 -> 10 | L5: =(H5/1000000)*J5+(I5/1000000)*K5 -> 3150 | M5: =IFERROR(L5/C5,0) -> 0.0105 | N5: =Inputs!H16 -> Network Operations
A6: =Inputs!A17 -> GLC-DocSum | B6: =Inputs!B17 -> Shipment-document summarizer | C6: =Inputs!C17 -> 500000 | D6: =Inputs!D17 -> 3000 | E6: =Inputs!E17 -> 500 | F6: =Inputs!F17 -> 1 | G6: =Inputs!G17 -> 1 | H6: =C6*D6*F6*G6 -> 1500000000 | I6: =C6*E6*F6*G6 -> 250000000 | J6: =Inputs!$B$3 -> 2.5 | K6: =Inputs!$B$4 -> 10 | L6: =(H6/1000000)*J6+(I6/1000000)*K6 -> 6250 | M6: =IFERROR(L6/C6,0) -> 0.0125 | N6: =Inputs!H17 -> Document Operations
A7: =Inputs!A18 -> GLC-ExceptionAgent | B7: =Inputs!B18 -> Exception-handling agent | C7: =Inputs!C18 -> 60000 | D7: =Inputs!D18 -> 900 | E7: =Inputs!E18 -> 250 | F7: =Inputs!F18 -> 1 | G7: =Inputs!G18 -> 12 | H7: =C7*D7*F7*G7 -> 648000000 | I7: =C7*E7*F7*G7 -> 180000000 | J7: =Inputs!$B$3 -> 2.5 | K7: =Inputs!$B$4 -> 10 | L7: =(H7/1000000)*J7+(I7/1000000)*K7 -> 3420 | M7: =IFERROR(L7/C7,0) -> 0.057 | N7: =Inputs!H18 -> Exception Operations
A8: Total | L8: =SUM(L4:L7) -> 22320 | M8: =IFERROR(L8/SUM(C4:C7),0) -> 0.0078041958

Sheet Agent Sensitivity
A1: Exception-agent token sensitivity
A2: These multipliers are planning cases, not an industry benchmark. Replace them with trace-based per-step inputs and outputs.
A4: Case | B4: Monthly tasks | C4: Base input tokens | D4: Base output tokens | E4: Calls/task | F4: Multiplier | G4: Monthly input tokens | H4: Monthly output tokens | I4: Input rate/1M | J4: Output rate/1M | K4: Monthly cost | L4: Delta vs base
A5: Low | B5: =Inputs!C18 -> 60000 | C5: =Inputs!D18 -> 900 | D5: =Inputs!E18 -> 250 | E5: =Inputs!F18 -> 1 | F5: =Inputs!B5 -> 5 | G5: =B5*C5*E5*F5 -> 270000000 | H5: =B5*D5*E5*F5 -> 75000000 | I5: =Inputs!$B$3 -> 2.5 | J5: =Inputs!$B$4 -> 10 | K5: =(G5/1000000)*I5+(H5/1000000)*J5 -> 1425 | L5: =K5-$K$6 -> -1995
A6: Base | B6: =Inputs!C18 -> 60000 | C6: =Inputs!D18 -> 900 | D6: =Inputs!E18 -> 250 | E6: =Inputs!F18 -> 1 | F6: =Inputs!B6 -> 12 | G6: =B6*C6*E6*F6 -> 648000000 | H6: =B6*D6*E6*F6 -> 180000000 | I6: =Inputs!$B$3 -> 2.5 | J6: =Inputs!$B$4 -> 10 | K6: =(G6/1000000)*I6+(H6/1000000)*J6 -> 3420 | L6: =K6-$K$6 -> 0
A7: High | B7: =Inputs!C18 -> 60000 | C7: =Inputs!D18 -> 900 | D7: =Inputs!E18 -> 250 | E7: =Inputs!F18 -> 1 | F7: =Inputs!B7 -> 30 | G7: =B7*C7*E7*F7 -> 1620000000 | H7: =B7*D7*E7*F7 -> 450000000 | I7: =Inputs!$B$3 -> 2.5 | J7: =Inputs!$B$4 -> 10 | K7: =(G7/1000000)*I7+(H7/1000000)*J7 -> 8550 | L7: =K7-$K$6 -> 5130

Sheet Chargeback & Quotas
A1: Cost allocation and quota guardrails
A2: Chargeback/showback uses invoice-reconciled cost. API gateway limits are technical controls and may not be perfectly exact in distributed enforcement.
A4: Cost center | B4: Application ID | C4: Monthly cost | D4: Monthly budget | E4: Budget utilization | F4: 70% alert | G4: 85% escalation | H4: 100% quota | I4: Recommended counter key | J4: Control mode | K4: Owner action
A5: ='Token Cost Model'!N4 -> Customer Experience | B5: ='Token Cost Model'!A4 -> GLC-CX-Chat | C5: ='Token Cost Model'!L4 -> 9500 | D5: =Inputs!I15 -> 12000 | E5: =IFERROR(C5/D5,0) -> 0.79166667 | F5: =D5*Inputs!$B$8 -> 8400 | G5: =D5*Inputs!$B$9 -> 10200 | H5: =D5*Inputs!$B$10 -> 12000 | I5: =B5&"|"&A5 -> GLC-CX-Chat|Customer Experience | J5: Alert + token-rate limit; period quota where business-safe | K5: Investigate driver, optimize, or request time-limited exception
A6: ='Token Cost Model'!N5 -> Network Operations | B6: ='Token Cost Model'!A5 -> GLC-NetAssist | C6: ='Token Cost Model'!L5 -> 3150 | D6: =Inputs!I16 -> 8000 | E6: =IFERROR(C6/D6,0) -> 0.39375 | F6: =D6*Inputs!$B$8 -> 5600 | G6: =D6*Inputs!$B$9 -> 6800 | H6: =D6*Inputs!$B$10 -> 8000 | I6: =B6&"|"&A6 -> GLC-NetAssist|Network Operations
A7: ='Token Cost Model'!N6 -> Document Operations | B7: ='Token Cost Model'!A6 -> GLC-DocSum | C7: ='Token Cost Model'!L6 -> 6250 | D7: =Inputs!I17 -> 15000 | E7: =IFERROR(C7/D7,0) -> 0.41666667 | F7: =D7*Inputs!$B$8 -> 10500 | G7: =D7*Inputs!$B$9 -> 12750 | H7: =D7*Inputs!$B$10 -> 15000 | I7: =B7&"|"&A7 -> GLC-DocSum|Document Operations
A8: ='Token Cost Model'!N7 -> Exception Operations | B8: ='Token Cost Model'!A7 -> GLC-ExceptionAgent | C8: ='Token Cost Model'!L7 -> 3420 | D8: =Inputs!I18 -> 15000 | E8: =IFERROR(C8/D8,0) -> 0.228 | F8: =D8*Inputs!$B$8 -> 10500 | G8: =D8*Inputs!$B$9 -> 12750 | H8: =D8*Inputs!$B$10 -> 15000 | I8: =B8&"|"&A8 -> GLC-ExceptionAgent|Exception Operations
A10: Portfolio total | C10: =SUM(C5:C8) -> 22320 | D10: =SUM(D5:D8) -> 50000 | E10: =IFERROR(C10/D10,0) -> 0.4464

Sheet Optimization Scenarios
A1: Optimization planning with quality and safety guardrails
A2: Estimated reductions are planning assumptions. Validate each change with the approved evaluation suite and production telemetry.
A4: Tactic | B4: Applicable workload | C4: Estimated reduction | D4: Baseline monthly cost | E4: Estimated savings | F4: Optimized cost | G4: Implementation note | H4: Quality guardrail | I4: Safety/privacy guardrail | J4: Evidence source
A5: Prompt and tool-schema reduction | B5: All, especially agent | C5: 0.08 | D5: ='Token Cost Model'!$L$8 -> 22320 | E5: =C5*D5 -> 1785.6 | F5: =D5-E5 -> 20534.4 | G5: Remove unused tool definitions and compress stable instructions | H5: No >2-point task-quality decline | I5: No new policy or safety failures | J5: Trace token breakdown + evaluation suite
A6: Model routing/tiering | B6: Chat and summarization | C6: 0.1 | D6: ='Token Cost Model'!$L$8 -> 22320 | E6: =C6*D6 -> 2232 | F6: =D6-E6 -> 20088 | G6: Route approved low-complexity tasks to a lower-cost deployment | H6: Quality threshold by task class | I6: Maintain content-safety and data-boundary controls | J6: A/B evaluation + cost telemetry
A7: Caching where supported | B7: Repeated prompts/retrieval | C7: 0.05 | D7: ='Token Cost Model'!$L$8 -> 22320 | E7: =C7*D7 -> 1116 | F7: =D7-E7 -> 21204 | G7: Cache stable prompts or retrieval results with expiry and data-scope keys | H7: Freshness and correctness checks | I7: No cross-user or cross-tenant data leakage | J7: Cache hit/miss + privacy tests
A8: Retry and output controls | B8: Agent and assistants | C8: 0.04 | D8: ='Token Cost Model'!$L$8 -> 22320 | E8: =C8*D8 -> 892.8 | F8: =D8-E8 -> 21427.2 | G8: Set retry ceilings, max tool iterations, and response-length limits | H8: No material completion loss | I8: Escalate instead of unsafe repeated execution | J8: Retry count + evaluator failure rate
A10: Combined planning case | C10: =MIN(SUM(C5:C8),0.5) -> 0.27 | D10: ='Token Cost Model'!$L$8 -> 22320 | E10: =C10*D10 -> 6026.4 | F10: =D10-E10 -> 16293.6

Sheet Sources
A1: Validation sources and implementation notes
A3: Topic | B3: Source | C3: URL | D3: Use in workbook/course
A4: Token limits | B4: Microsoft Learn — llm-token-limit policy | C4: https://learn.microsoft.com/en-us/azure/api-management/llm-token-limit-policy | D4: Rate limit returns 429; quota returns 403; actual total tokens cannot be fully predicted before completion.
A5: Rate limits | B5: Microsoft Learn — rate-limit-by-key | C5: https://learn.microsoft.com/en-us/azure/api-management/rate-limit-by-key-policy | D5: Distributed throttling is not completely accurate.
A6: Quotas | B6: Microsoft Learn — quota-by-key | C6: https://learn.microsoft.com/en-us/azure/api-management/quota-by-key-policy | D6: Quota can briefly overshoot after service-platform restart.
A7: Agent traces | B7: Microsoft Foundry — agent tracing | C7: https://learn.microsoft.com/en-us/azure/foundry/observability/concepts/trace-agent-concept | D7: Traces include inputs, outputs, tools, retries, latency, and costs; check preview status.
A8: Data Zone | B8: Microsoft Foundry — region availability | C8: https://learn.microsoft.com/en-us/azure/foundry/foundry-models/concepts/models-sold-directly-by-azure-region-availability | D8: Data Zone processing can occur anywhere within the selected zone.
A9: Incident response | B9: Microsoft Cloud Security Benchmark v2 | C9: https://learn.microsoft.com/en-us/security/benchmark/azure/mcsb-v2-incident-response | D9: Prioritize by asset criticality, business impact, threat severity, and regulatory requirements.
A10: EU AI Act | B10: Regulation (EU) 2024/1689 | C10: https://eur-lex.europa.eu/eli/reg/2024/1689/oj | D10: High-risk classification is use-case specific; applicable high-risk logs have a six-month minimum.
A11: GDPR | B11: Regulation (EU) 2016/679 | C11: https://eur-lex.europa.eu/eli/reg/2016/679/oj | D11: Data minimization, storage limitation, and automated-decision safeguards.
A12: LGPD | B12: Official English translation | C12: https://www.gov.br/anpd/pt-br/centrais-de-conteudo/outros-documentos-e-publicacoes-institucionais/lgpd-en-lei-no-13-709-capa.pdf | D12: Purpose-based retention and automated-decision review considerations.
A13: DPDP | B13: MeitY — DPDP Rules 2025 | C13: https://www.meity.gov.in/documents/act-and-policies/digital-personal-data-protection-rules-2025-gDOxUjMtQWa | D13: Validate current Indian requirements and implementation timeline.
